Pras_Server/CheckPDBatoms.py
Pras_Server/DownloadPDB.py
Pras_Server/FixHeavyAtoms.py
Pras_Server/ForcefieldParam.py
Pras_Server/LinearAlgebra.py
Pras_Server/MissingHeavyAtoms.py
Pras_Server/MissingHydrogenAtoms.py
Pras_Server/PDBID.py
Pras_Server/PRAS.py
Pras_Server/PotentialEnergy.py
Pras_Server/RamaChandra.py
Pras_Server/ReadMaster.py
Pras_Server/ReadStructure.py
Pras_Server/ReadmmCIF.py
Pras_Server/RunType.py
Pras_Server/SecondaryStructure.py
Pras_Server/__init__.py
Pras_Server/_version.py
Pras_Server/data/KD.dat
Pras_Server/run_PRAS_with_FASPR/1aho.pdb
Pras_Server/run_PRAS_with_FASPR/PRAS_with_FASPR.pdf
Pras_Server/run_PRAS_with_FASPR/linux_example.py
Pras_Server/run_PRAS_with_FASPR/syntax.txt
Pras_Server-1.2.1.dist-info/LICENSE.txt
Pras_Server-1.2.1.dist-info/METADATA
Pras_Server-1.2.1.dist-info/WHEEL
Pras_Server-1.2.1.dist-info/top_level.txt
Pras_Server-1.2.1.dist-info/RECORD
