Metadata-Version: 2.1
Name: Pras-Server
Version: 1.2.1
Summary: A webserver to repair PDB files
Home-page: https://www.protein-science.com/
Author: Osita S. Nnyigide
Author-email: osita@protein-science.com
Classifier: License :: OSI Approved :: MIT License
Classifier: Programming Language :: Python :: 3
Classifier: Programming Language :: Python :: 3.7
Requires-Python: >=3.6, <4
License-File: LICENSE.txt
Requires-Dist: numpy
Requires-Dist: matplotlib
Requires-Dist: setuptools
